{
    "@context": "http://iiif.io/api/presentation/3/context.json",
    "id": "https://tu-delft-heritage.github.io/beeldbank-data/manifests/2fcb3986-bb1e-4e11-b88e-2279082a7cc2.json",
    "type": "Manifest",
    "label": {
        "nl": [
            "Toestel voor het aanvragen van boeken met de Bibliofoon in de bibliotheek van de Technische Hogeschool Delft"
        ]
    },
    "metadata": [
        {
            "label": {
                "en": [
                    "Title"
                ],
                "nl": [
                    "Titel"
                ]
            },
            "value": {
                "nl": [
                    "Toestel voor het aanvragen van boeken met de Bibliofoon in de bibliotheek van de Technische Hogeschool Delft"
                ]
            }
        },
        {
            "label": {
                "en": [
                    "Description"
                ],
                "nl": [
                    "Beschrijving"
                ]
            },
            "value": {
                "nl": [
                    "Jaar 1960 is geschat."
                ]
            }
        },
        {
            "label": {
                "en": [
                    "Year"
                ],
                "nl": [
                    "Jaar"
                ]
            },
            "value": {
                "nl": [
                    "1960"
                ]
            }
        },
        {
            "label": {
                "en": [
                    "Format"
                ],
                "nl": [
                    "Formaat"
                ]
            },
            "value": {
                "nl": [
                    "image"
                ]
            }
        }
    ],
    "items": [
        {
            "id": "https://tu-delft-heritage.github.io/beeldbank-data/manifests/2fcb3986-bb1e-4e11-b88e-2279082a7cc2/canvas/0",
            "type": "Canvas",
            "height": 2480,
            "width": 3100,
            "items": [
                {
                    "id": "https://tu-delft-heritage.github.io/beeldbank-data/manifests/2fcb3986-bb1e-4e11-b88e-2279082a7cc2/canvas/0/annotation-page",
                    "type": "AnnotationPage",
                    "items": [
                        {
                            "id": "https://dlc.services/iiif-img/v3/7/15/9087baec-3f65-4247-8644-49090ad75f4e",
                            "type": "Annotation",
                            "motivation": "painting",
                            "target": "https://tu-delft-heritage.github.io/beeldbank-data/manifests/2fcb3986-bb1e-4e11-b88e-2279082a7cc2/canvas/0",
                            "body": {
                                "id": "https://dlc.services/iiif-img/v3/7/15/9087baec-3f65-4247-8644-49090ad75f4e/full/max/0/default.jpg",
                                "type": "Image",
                                "format": "image/jpeg",
                                "height": 2480,
                                "width": 3100,
                                "service": [
                                    {
                                        "@context": "http://iiif.io/api/image/3/context.json",
                                        "id": "https://dlc.services/iiif-img/v3/7/15/9087baec-3f65-4247-8644-49090ad75f4e",
                                        "type": "ImageService3",
                                        "profile": "level2"
                                    }
                                ]
                            }
                        }
                    ]
                }
            ]
        },
        {
            "id": "https://tu-delft-heritage.github.io/beeldbank-data/manifests/2fcb3986-bb1e-4e11-b88e-2279082a7cc2/canvas/1",
            "type": "Canvas",
            "height": 2480,
            "width": 3100,
            "items": [
                {
                    "id": "https://tu-delft-heritage.github.io/beeldbank-data/manifests/2fcb3986-bb1e-4e11-b88e-2279082a7cc2/canvas/1/annotation-page",
                    "type": "AnnotationPage",
                    "items": [
                        {
                            "id": "https://dlc.services/iiif-img/v3/7/15/493b2576-f3a2-44f0-b307-df3ad08409e2",
                            "type": "Annotation",
                            "motivation": "painting",
                            "target": "https://tu-delft-heritage.github.io/beeldbank-data/manifests/2fcb3986-bb1e-4e11-b88e-2279082a7cc2/canvas/1",
                            "body": {
                                "id": "https://dlc.services/iiif-img/v3/7/15/493b2576-f3a2-44f0-b307-df3ad08409e2/full/max/0/default.jpg",
                                "type": "Image",
                                "format": "image/jpeg",
                                "height": 2480,
                                "width": 3100,
                                "service": [
                                    {
                                        "@context": "http://iiif.io/api/image/3/context.json",
                                        "id": "https://dlc.services/iiif-img/v3/7/15/493b2576-f3a2-44f0-b307-df3ad08409e2",
                                        "type": "ImageService3",
                                        "profile": "level2"
                                    }
                                ]
                            }
                        }
                    ]
                }
            ]
        }
    ]
}